basics/pipelining2/processor.v
`timescale 1ns/1ps
module pipe_ex2 (rs1,rs2,rd,func,addr,clk1,clk2,wr,Z);

    input[3:0] rs1,rs2,rd,func;
    input[7:0] addr;
    input clk1,clk2,wr;
    //input[15:0] wrdata_reg;
   // input[15:0] wrdata_mem;
    output[15:0] Z;

    parameter ADD = 4'b0000,SUB = 4'b0001,MUL = 4'b0010,SELA = 4'b0011,
    SELB = 4'b0100,AND = 4'b0101,OR = 4'b0110,XOR = 4'b0111,NEGA = 4'b1000,NEGB = 4'b1001,
    SRA = 4'b1010,SLA = 4'b1011;

    reg [15:0] A,B;
    //reg [15:0] rddata1_mem;
    reg [3:0] L12f;
    reg [7:0] L12addr;
    reg [3:0] L12rd;
    reg L12wr;

    reg [7:0] L23addr;
    reg [3:0] L23rd;
    reg L23wr;
    reg [15:0] L23Z;

    reg [7:0] L34addr;
    reg L34wr;
    reg [15:0] L34Z;


    reg [15:0] R[15:0];
    reg [15:0] mem[255:0];

    assign Z = L34Z;

    always @(posedge clk1) begin
        A <=#2 R[rs1];
        B <=#2 R[rs2];

        L12f<=#2 func;
        L12rd<=#2 rd;
        L12addr<=#2 addr;
        L12wr<=#2wr;
    end

    always @(posedge clk2) begin
        case (L12f)
           ADD : L23Z <=#2 A + B;
           SUB : L23Z <=#2 A - B;
           MUL : L23Z <=#2 A * B;
           SELA : L23Z <=#2 A ;
           SELB : L23Z <=#2 B;
           AND : L23Z <=#2 A & B;
           OR : L23Z <=#2 A | B;
           XOR : L23Z <=#2 A ^ B;
           NEGA : L23Z <=#2 ~A;
           NEGB : L23Z <=#2 ~B;
           SRA : L23Z <=#2 A >>1 ;
           SLA : L23Z <=#2 A <<1 ;
        endcase
        L23rd<=#2 L12rd;
        L23addr<=#2 L12addr;
        L23wr<=#2L12wr;
    end

    always @(posedge clk1) begin
        R[L23rd] <=#2 L23Z;
        L34Z<=#2 L23Z;
        L34addr<=#2 L23addr;
        L34wr<=#2L23wr;
    end

    always @(posedge clk2) begin
        if (L34wr) begin
        mem[L34addr] <=#2 L34Z;
        end
    end
endmodule

basics/pipelining2/ptest.v
`timescale 1ns/1ps
module DUT;
    reg [3:0] rs1,rs2,func,rd;
    reg [7:0] addr;
    reg clk1,clk2,wr;
    wire [15:0] Z;
    integer k;
    pipe_ex2 P1(rs1,rs2,rd,func,addr,clk1,clk2,wr,Z);

    initial 
    begin
    clk1=0; clk2 =0;
    repeat(20)
    begin
        #5 clk1 = 1; #5 clk1 =0;
        #5 clk2 = 1; #5 clk2 =0;
    end
    end

    initial 
    begin
        for (k=0 ; k<16; k=k+1 ) 
        begin
            P1.R[k] = k;
        end    
    end

    initial
    begin
        wr =1'b0;
        rs1 = 4'b0000;
        rs2 = 4'b0000;
        rd = 4'b0000;
        addr = 8'b00000000;
        func = 4'b0000;

        #1
        wr =1'b1;
        rs1 = 4'b0000;
        rs2 = 4'b0001;
        rd = 4'b1010;
        addr = 8'b01010101;
        func = 4'b0000;//add

        #20
        rs1 = 4'b0010;
        rs2 = 4'b0011;
        rd = 4'b1011;
        addr = 8'b01010111;
        func = 4'b0001;//sub
        
        #20
        rs1 = 4'b0100;
        rs2 = 4'b0101;
        rd = 4'b1100;
        addr = 8'b01010110;
        func = 4'b0010;//MUL
        
        #20
        rs1 = 4'b0110;
        rs2 = 4'b0111;
        rd = 4'b1101;
        addr = 8'b01010100;
        func = 4'b0011;//SELA
        
        #20
        rs1 = 4'b1000;
        rs2 = 4'b1001;
        rd = 4'b1110;
        addr = 8'b01010001;
        func = 4'b0100;//SELB

        #120
        $finish;
    end

        initial begin
            $monitor("Time : %d, Z : %d", $time , Z);
            $dumpvars(0,DUT); $dumpfile("dump.vcd");
        end

endmodule

basics/pipelining2/dump.vcd
$date
	Mon May 18 19:51:17 2026
$end
$version
	Icarus Verilog
$end
$timescale
	1ps
$end
$scope module DUT $end
$var wire 16 ! Z [15:0] $end
$var reg 8 " addr [7:0] $end
$var reg 1 # clk1 $end
$var reg 1 $ clk2 $end
$var reg 4 % func [3:0] $end
$var integer 32 & k [31:0] $end
$var reg 4 ' rd [3:0] $end
$var reg 4 ( rs1 [3:0] $end
$var reg 4 ) rs2 [3:0] $end
$var reg 1 * wr $end
$scope module P1 $end
$var wire 16 + Z [15:0] $end
$var wire 8 , addr [7:0] $end
$var wire 1 - clk1 $end
$var wire 1 . clk2 $end
$var wire 4 / func [3:0] $end
$var wire 4 0 rd [3:0] $end
$var wire 4 1 rs1 [3:0] $end
$var wire 4 2 rs2 [3:0] $end
$var wire 1 3 wr $end
$var reg 16 4 A [15:0] $end
$var reg 16 5 B [15:0] $end
$var reg 8 6 L12addr [7:0] $end
$var reg 4 7 L12f [3:0] $end
$var reg 4 8 L12rd [3:0] $end
$var reg 1 9 L12wr $end
$var reg 16 : L23Z [15:0] $end
$var reg 8 ; L23addr [7:0] $end
$var reg 4 < L23rd [3:0] $end
$var reg 1 = L23wr $end
$var reg 16 > L34Z [15:0] $end
$var reg 8 ? L34addr [7:0] $end
$var reg 1 @ L34wr $end
$upscope $end
$upscope $end
$enddefinitions $end
#0
$dumpvars
x@
bx ?
bx >
x=
bx <
bx ;
bx :
x9
bx 8
bx 7
bx 6
bx 5
bx 4
03
b0 2
b0 1
b0 0
b0 /
0.
0-
b0 ,
bx +
0*
b0 )
b0 (
b0 '
b10000 &
b0 %
0$
0#
b0 "
bx !
$end
#1000
b1010101 "
b1010101 ,
b1010 '
b1010 0
b1 )
b1 2
1*
13
#5000
1#
1-
#7000
19
b1010101 6
b1010 8
b0 7
b1 5
b0 4
#10000
0#
0-
#15000
1$
1.
#17000
1=
b1010101 ;
b1010 <
b1 :
#20000
0$
0.
#21000
b1 %
b1 /
b1010111 "
b1010111 ,
b1011 '
b1011 0
b11 )
b11 2
b10 (
b10 1
#25000
1#
1-
#27000
1@
b1010101 ?
b1 >
b1 !
b1 +
b1010111 6
b1011 8
b1 7
b11 5
b10 4
#30000
0#
0-
#35000
1$
1.
#37000
b1010111 ;
b1011 <
b1111111111111111 :
#40000
0$
0.
#41000
b10 %
b10 /
b1010110 "
b1010110 ,
b1100 '
b1100 0
b101 )
b101 2
b100 (
b100 1
#45000
1#
1-
#47000
b1010110 6
b1100 8
b10 7
b101 5
b100 4
b1010111 ?
b1111111111111111 >
b1111111111111111 !
b1111111111111111 +
#50000
0#
0-
#55000
1$
1.
#57000
b1010110 ;
b1100 <
b10100 :
#60000
0$
0.
#61000
b11 %
b11 /
b1010100 "
b1010100 ,
b1101 '
b1101 0
b111 )
b111 2
b110 (
b110 1
#65000
1#
1-
#67000
b1010110 ?
b10100 >
b10100 !
b10100 +
b1010100 6
b1101 8
b11 7
b111 5
b110 4
#70000
0#
0-
#75000
1$
1.
#77000
b1010100 ;
b1101 <
b110 :
#80000
0$
0.
#81000
b100 %
b100 /
b1010001 "
b1010001 ,
b1110 '
b1110 0
b1001 )
b1001 2
b1000 (
b1000 1
#85000
1#
1-
#87000
b1010001 6
b1110 8
b100 7
b1001 5
b1000 4
b1010100 ?
b110 >
b110 !
b110 +
#90000
0#
0-
#95000
1$
1.
#97000
b1010001 ;
b1110 <
b1001 :
#100000
0$
0.
#105000
1#
1-
#107000
b1010001 ?
b1001 >
b1001 !
b1001 +
