FSM/RYGtrafficlight/RYG.v
module RGY(clock, light);
input clock;
output reg[0:2] light;
parameter S0=0, S1=1, S2=2;
parameter red=3'b100, green=3'b010, yellow=3'b001;
reg[1:0] state;

always @(posedge clock) //use of clk posedge to instantiate state suggest flip flop(sequential - <=)
    case(state)
    S0 : state <= S1;
    S1 : state <= S2;
    S2 : state <= S0;
    default : state <= S0;
    endcase
    
always @(state) // state changes the colour should change hence it acts as mux 8*1
    case(state)
    S0 : light = red;
    S1 : light = green;
    S2 : light = yellow;
    default : light = red;
    endcase
endmodule

FSM/RYGtrafficlight/RYGtest.v
`timescale 1ns/1ps
module DUT();
    reg clock; 
    wire [0:2] light;
    RGY R1 (clock, light);

    always #5 clock = ~clock;

    initial begin
        clock = 0;
        #100 $finish;
    end

    initial begin
        $monitor(" time is %d and the light colour is %d" , $time , light);
        $dumpfile("RYGlight.vcd");
        $dumpvars(0,DUT);

    end
endmodule

FSM/RYGtrafficlight/RYGlight.vcd
$date
	Sun Aug 02 23:29:52 2026
$end
$version
	Icarus Verilog
$end
$timescale
	1ps
$end
$scope module DUT $end
$var wire 3 ! light [0:2] $end
$var reg 1 " clock $end
$scope module R1 $end
$var wire 1 # clock $end
$var reg 3 $ light [0:2] $end
$var reg 2 % state [1:0] $end
$upscope $end
$upscope $end
$enddefinitions $end
#0
$dumpvars
bx %
bx $
0#
0"
bx !
$end
#5000
b100 $
b100 !
b0 %
1"
1#
#10000
0"
0#
#15000
b10 $
b10 !
b1 %
1"
1#
#20000
0"
0#
#25000
b1 $
b1 !
b10 %
1"
1#
#30000
0"
0#
#35000
b100 $
b100 !
b0 %
1"
1#
#40000
0"
0#
#45000
b10 $
b10 !
b1 %
1"
1#
#50000
0"
0#
#55000
b1 $
b1 !
b10 %
1"
1#
#60000
0"
0#
#65000
b100 $
b100 !
b0 %
1"
1#
#70000
0"
0#
#75000
b10 $
b10 !
b1 %
1"
1#
#80000
0"
0#
#85000
b1 $
b1 !
b10 %
1"
1#
#90000
0"
0#
#95000
b100 $
b100 !
b0 %
1"
1#
