basics/pipelinig/f2.v
`timescale 1ns/1ps
module pipe_ex (F,A,B,C,D,clk);
    parameter N = 10;
    input [N-1:0] A,B,C,D;
    input clk;
    output [N-1:0] F;
    reg[N-1:0] L12x1,L12x2,L12D,L23x1,L23D,L34x1;

    assign F = L34x1;

    always @(posedge clk) 
    begin
        L12x1 <=#4 A + B;
        L12x2 <=#4 C - D;
        L12D <= D;
    end

    always @(posedge clk) begin
        L23x1 <=#4 L12x1 + L12x2;
        L23D <= L12D;
    end

    always @(posedge clk) begin
        L34x1<=#6 L23x1*L23D;
    end
        
endmodule

basics/pipelinig/ftest2.v
module DUT;

    parameter N =10;
    reg [N-1:0] A,B,C,D;
    reg clk;

    wire[N-1:0] F;
    pipe_ex P1(F,A,B,C,D,clk);

    always #5 clk = ~clk;

    initial begin
    clk=0;
    A=0;B=0;C=0;D=0;

    #10
    A=10; B=15; C=10; D=10;

    #10
    A=10; B=10; C=5; D=5;

    #10
    A=5; B=15; C=20; D=5;
    
    #10
    A=10; B=5; C=10; D=5;
    
    #10
    A=10; B=10; C=5; D=10;

    #50

    $finish;
    end

    initial begin
        $monitor("Time: %d,F : %d", $time, F);
        $dumpvars(0,DUT); $dumpfile("dump.vcd");
    end
endmodule

basics/pipelinig/dump.vcd
$date
	Tue May 12 14:08:23 2026
$end
$version
	Icarus Verilog
$end
$timescale
	1ps
$end
$scope module DUT $end
$var wire 10 ! F [9:0] $end
$var reg 10 " A [9:0] $end
$var reg 10 # B [9:0] $end
$var reg 10 $ C [9:0] $end
$var reg 10 % D [9:0] $end
$var reg 1 & clk $end
$scope module P1 $end
$var wire 10 ' A [9:0] $end
$var wire 10 ( B [9:0] $end
$var wire 10 ) C [9:0] $end
$var wire 10 * D [9:0] $end
$var wire 10 + F [9:0] $end
$var wire 1 , clk $end
$var reg 10 - L12D [9:0] $end
$var reg 10 . L12x1 [9:0] $end
$var reg 10 / L12x2 [9:0] $end
$var reg 10 0 L23D [9:0] $end
$var reg 10 1 L23x1 [9:0] $end
$var reg 10 2 L34x1 [9:0] $end
$upscope $end
$upscope $end
$enddefinitions $end
#0
$dumpvars
bx 2
bx 1
bx 0
bx /
bx .
bx -
0,
bx +
b0 *
b0 )
b0 (
b0 '
0&
b0 %
b0 $
b0 #
b0 "
bx !
$end
#5000
b0 -
1&
1,
#9000
b0 /
b0 .
#10000
0&
0,
b1010 %
b1010 *
b1010 $
b1010 )
b1111 #
b1111 (
b1010 "
b1010 '
#15000
b0 0
b1010 -
1&
1,
#19000
b0 1
b11001 .
#20000
0&
0,
b101 %
b101 *
b101 $
b101 )
b1010 #
b1010 (
#25000
b101 -
b1010 0
1&
1,
#29000
b10100 .
b11001 1
#30000
0&
0,
b10100 $
b10100 )
b1111 #
b1111 (
b101 "
b101 '
#31000
b0 2
b0 !
b0 +
#35000
b101 0
1&
1,
#39000
b10100 1
b1111 /
#40000
0&
0,
b1010 $
b1010 )
b101 #
b101 (
b1010 "
b1010 '
#41000
b11111010 2
b11111010 !
b11111010 +
#45000
1&
1,
#49000
b101 /
b1111 .
b100011 1
#50000
0&
0,
b1010 %
b1010 *
b101 $
b101 )
b1010 #
b1010 (
#51000
b1100100 2
b1100100 !
b1100100 +
#55000
b1010 -
1&
1,
#59000
b10100 1
b1111111011 /
b10100 .
#60000
0&
0,
#61000
b10101111 2
b10101111 !
b10101111 +
#65000
b1010 0
1&
1,
#69000
b1111 1
#70000
0&
0,
#71000
b1100100 2
b1100100 !
b1100100 +
#75000
1&
1,
#80000
0&
0,
#81000
b10010110 2
b10010110 !
b10010110 +
