FIFO/asynchronous_fifo/write_logic.v
module writeptr (wclk,wrst,wr_en,rptr_g,full,waddr_g,wptr_b);
    input wclk,wrst,wr_en;
    input [3:0] rptr_g;
    output full;
    output [3:0] waddr_g,wptr_b;

    reg [3:0] wbin,wgray;
    wire [3:0] wbin_next,wgray_next;

    always @(posedge wclk or negedge wrst) begin
        if (!wrst) begin
            {wbin,wgray} <= 0;
        end
        else begin
            {wbin,wgray} <= {wbin_next,wgray_next};
        end
    end

    assign wbin_next = wbin + (wr_en && !full);
    assign wgray_next = (wbin_next >> 1) ^ (wbin_next);
    assign waddr_g = wgray;
    assign wptr_b = wbin;

    assign full = ((wgray[1:0] == rptr_g [1:0]) && (~wgray[3:2] == rptr_g [3:2]));
endmodule

FIFO/asynchronous_fifo/read_logic.v
module readptr (clk,rrst,rinc,wptr_g,empty,raddr_g,rptr_b);
    input clk,rrst,rinc;
    input [3:0] wptr_g;
    output empty;
    output [3:0] raddr_g,rptr_b;

    reg [3:0] rbin,rgray;
    wire [3:0] rbin_next,rgray_next;

    always @(posedge clk or negedge rrst) begin
        if (!rrst) begin
            {rbin,rgray} <= 0;
        end
        else begin
            rbin <= rbin_next;
            rgray <= rgray_next;
        end
    end

    assign empty = (wptr_g == rgray);
    assign rbin_next = rbin + (rinc && !empty);
    assign rgray_next = (rbin_next >> 1) ^ (rbin_next);
    assign raddr_g = rgray;
    assign rptr_b = rbin;
endmodule

FIFO/asynchronous_fifo/twoff_synchronisor.v
module synchronisor (clk,rst,din,q2);
    input clk,rst;
    input [3:0] din;
    output reg [3:0] q2;

    reg [3:0] q1;

    always @(posedge clk or negedge rst) begin
        if (!rst) begin
            q2 <= 0;
            q1 <=0 ;
        end

        else begin
            {q2,q1} <= {q1,din};
        end
    end
endmodule

FIFO/asynchronous_fifo/fifomemory.v
module fifomem (wclk,rclk,full,empty,rinc,wr_en,wr_data,wr_ptr_b,rd_data,rd_ptr_b);
    input rclk,wclk,full,empty,rinc,wr_en;
    input [31:0] wr_data;
    input [2:0] wr_ptr_b;
    output reg [31:0] rd_data;
    input [2:0] rd_ptr_b;

    reg [31:0] mem [0:7];

    always @(posedge wclk) begin
        if(!full && wr_en)
        mem[wr_ptr_b] <= wr_data;
    end

    always @(posedge rclk) begin
        if(!empty && rinc)
        rd_data <= mem[rd_ptr_b];
    end
endmodule

FIFO/asynchronous_fifo/fifo.v
module FIFO(rclk,wclk,rinc,wr_en,wrst,rrst,wr_data,rd_data);

    input rclk,wclk,rinc,wr_en,wrst,rrst;
    input [31:0] wr_data;
    output [31:0] rd_data;

    wire [3:0] wptr_b,rptr_b,w2rptr_g,r2wptr_g,wptr_g,rptr_g;
    
    fifomem memry (wclk,rclk,full,empty,rinc,wr_en,wr_data,wptr_b[2:0],rd_data,rptr_b[2:0]);
    synchronisor w2r (rclk,rrst,w2rptr_g,wptr_g);
    synchronisor r2w (wclk,wrst,r2wptr_g,rptr_g);
    readptr read_block (rclk,rrst,rinc,wptr_g,empty,r2wptr_g,rptr_b);
    writeptr write_block (wclk,wrst,wr_en,rptr_g,full,w2rptr_g,wptr_b);
endmodule

FIFO/asynchronous_fifo/fifotest.v
`timescale 1ns/1ps
module DUT();

    reg rclk,wclk,rinc,wr_en,wrst,rrst;
    reg [31:0] wr_data;
    wire [31:0] rd_data;

    FIFO F1 (rclk,wclk,rinc,wr_en,wrst,rrst,wr_data,rd_data);

    always #5 wclk = ~wclk;
    always #5000 rclk = ~rclk;

    initial begin
        //test for scenario 1
        #97000
        $display(" empty port is %d" , F1.read_block.empty);// checking empty port
        $display("value of fifo 1st location is %d" , F1.memry.mem[0]);
        $display("value of fifo 8th location is %d" , F1.memry.mem[7]);

        //test for scenario 2
        /*
        #200
        $display(" full port is %d" , F1.write_block.full);// checking full port
        $display("value of fifo 1st location is %d" , F1.memry.mem[0]);// checking data of 1st location
        */


    end

    initial begin
        wclk = 0;
        rclk = 0;
        wrst = 1;
        rrst = 1;

        #10 wrst = 0;
        rrst = 0;
        #1 wrst = 1;
        rrst = 1;
        wr_en = 1;
        // scenario 1
        // checking the functionality of write ptr and read ptr ----1
        rinc = 1;
        wr_data = 4; //loaded data
        #10 wr_data = 8;
        #10 wr_data = 12;
        #10 wr_data = 16;
        #10 wr_data = 20;
        #10 wr_data = 24;
        #10 wr_data = 28;
        #10 wr_data = 32;
        #10 wr_en = 0;
        
        #100000 $finish;

        //scenario 2
        // checking full port functionality and simultaneously writing data after full stack
        /*
        wr_data = 4;
        #10 wr_data = 8;
        #10 wr_data = 12;
        #10 wr_data = 16;
        #10 wr_data = 20;
        #10 wr_data = 24;
        #10 wr_data = 28;
        #10 wr_data = 32;
        #10 wr_data = 36;// write 9th data trying to write after full

        #500 $finish;
        */


        // scenario 3
        // try to write upto some stack and then trying to read it after it gets empty
        /*
        wr_data = 4;
        #10 wr_data = 8;
        #10 wr_data = 12;
        #10 wr_data = 16;
        #10 wr_en = 0;
        rinc = 1;
        
        #70000
        $display("value of fifo 4th location is %d" , F1.memry.mem[3]);// checking data of 4th location
        $display("value of fifo 5th location is %d" , F1.memry.mem[4]);// checking data of 5th location
        $display("the data received at read terminal is %d" , rd_data); // it should be 16
        $display(" empty port is %d" , F1.read_block.empty);// checking empty port
        #100
        $finish;
        */

    end

    initial begin
        //checking values for scenario 1
        $monitor("the data received at read terminal is %d and time is %d" , rd_data , $time);
        $dumpfile("fifoo.vcd");
        $dumpvars(0,DUT);
    end
endmodule

FIFO/asynchronous_fifo/fifoo.vcd
$date
	Sun Aug 02 23:17:34 2026
$end
$version
	Icarus Verilog
$end
$timescale
	1ps
$end
$scope module DUT $end
$var wire 32 ! rd_data [31:0] $end
$var reg 1 " rclk $end
$var reg 1 # rinc $end
$var reg 1 $ rrst $end
$var reg 1 % wclk $end
$var reg 32 & wr_data [31:0] $end
$var reg 1 ' wr_en $end
$var reg 1 ( wrst $end
$scope module F1 $end
$var wire 1 ) empty $end
$var wire 1 * full $end
$var wire 4 + r2wptr_g [3:0] $end
$var wire 1 , rclk $end
$var wire 32 - rd_data [31:0] $end
$var wire 1 . rinc $end
$var wire 4 / rptr_b [3:0] $end
$var wire 4 0 rptr_g [3:0] $end
$var wire 1 1 rrst $end
$var wire 4 2 w2rptr_g [3:0] $end
$var wire 1 3 wclk $end
$var wire 4 4 wptr_b [3:0] $end
$var wire 4 5 wptr_g [3:0] $end
$var wire 32 6 wr_data [31:0] $end
$var wire 1 7 wr_en $end
$var wire 1 8 wrst $end
$scope module memry $end
$var wire 1 ) empty $end
$var wire 1 * full $end
$var wire 1 , rclk $end
$var wire 3 9 rd_ptr_b [2:0] $end
$var wire 1 . rinc $end
$var wire 1 3 wclk $end
$var wire 32 : wr_data [31:0] $end
$var wire 1 7 wr_en $end
$var wire 3 ; wr_ptr_b [2:0] $end
$var reg 32 < rd_data [31:0] $end
$upscope $end
$scope module w2r $end
$var wire 1 , clk $end
$var wire 4 = din [3:0] $end
$var wire 1 1 rst $end
$var reg 4 > q1 [3:0] $end
$var reg 4 ? q2 [3:0] $end
$upscope $end
$scope module r2w $end
$var wire 1 3 clk $end
$var wire 4 @ din [3:0] $end
$var wire 1 8 rst $end
$var reg 4 A q1 [3:0] $end
$var reg 4 B q2 [3:0] $end
$upscope $end
$scope module read_block $end
$var wire 1 , clk $end
$var wire 1 ) empty $end
$var wire 4 C raddr_g [3:0] $end
$var wire 4 D rbin_next [3:0] $end
$var wire 4 E rgray_next [3:0] $end
$var wire 1 . rinc $end
$var wire 4 F rptr_b [3:0] $end
$var wire 1 1 rrst $end
$var wire 4 G wptr_g [3:0] $end
$var reg 4 H rbin [3:0] $end
$var reg 4 I rgray [3:0] $end
$upscope $end
$scope module write_block $end
$var wire 1 * full $end
$var wire 4 J rptr_g [3:0] $end
$var wire 4 K waddr_g [3:0] $end
$var wire 4 L wbin_next [3:0] $end
$var wire 1 3 wclk $end
$var wire 4 M wgray_next [3:0] $end
$var wire 4 N wptr_b [3:0] $end
$var wire 1 7 wr_en $end
$var wire 1 8 wrst $end
$var reg 4 O wbin [3:0] $end
$var reg 4 P wgray [3:0] $end
$upscope $end
$upscope $end
$upscope $end
$enddefinitions $end
#0
$dumpvars
bx P
bx O
bx N
bx M
bx L
bx K
bx J
bx I
bx H
bx G
bx F
bx E
bx D
bx C
bx B
bx A
bx @
bx ?
bx >
bx =
bx <
bx ;
bx :
bx 9
18
x7
bx 6
bx 5
bx 4
03
bx 2
11
bx 0
bx /
x.
bx -
0,
bx +
x*
x)
1(
x'
bx &
0%
1$
x#
0"
bx !
$end
#5000
1%
13
#10000
b0 E
0*
b0 D
b0 9
b0 ;
b0 >
b0 ?
1)
b0 5
b0 G
b0 H
b0 /
b0 F
b0 I
b0 +
b0 @
b0 C
b0 O
b0 4
b0 N
b0 P
b0 2
b0 =
b0 K
b0 A
b0 B
b0 0
b0 J
0%
03
0$
01
0(
08
#11000
b1 M
b1 L
b100 &
b100 6
b100 :
1#
1.
1'
17
1$
11
1(
18
#15000
b11 M
b1 ;
b1 O
b10 L
b1 4
b1 N
b1 P
b1 2
b1 =
b1 K
1%
13
#20000
0%
03
#21000
b1000 &
b1000 6
b1000 :
#25000
b10 M
b10 ;
b10 O
b11 L
b10 4
b10 N
b11 P
b11 2
b11 =
b11 K
1%
13
#30000
0%
03
#31000
b1100 &
b1100 6
b1100 :
#35000
b110 M
b11 ;
b11 O
b100 L
b11 4
b11 N
b10 P
b10 2
b10 =
b10 K
1%
13
#40000
0%
03
#41000
b10000 &
b10000 6
b10000 :
#45000
b111 M
b100 ;
b100 O
b101 L
b100 4
b100 N
b110 P
b110 2
b110 =
b110 K
1%
13
#50000
0%
03
#51000
b10100 &
b10100 6
b10100 :
#55000
b101 M
b101 ;
b101 O
b110 L
b101 4
b101 N
b111 P
b111 2
b111 =
b111 K
1%
13
#60000
0%
03
#61000
b11000 &
b11000 6
b11000 :
#65000
b100 M
b110 ;
b110 O
b111 L
b110 4
b110 N
b101 P
b101 2
b101 =
b101 K
1%
13
#70000
0%
03
#71000
b11100 &
b11100 6
b11100 :
#75000
b1100 M
b111 ;
b111 O
b1000 L
b111 4
b111 N
b100 P
b100 2
b100 =
b100 K
1%
13
#80000
0%
03
#81000
b100000 &
b100000 6
b100000 :
#85000
1*
b1100 M
b0 ;
b1000 O
b1000 L
b1000 4
b1000 N
b1100 P
b1100 2
b1100 =
b1100 K
1%
13
#90000
0%
03
#91000
0'
07
