Datapath_and_controller/HCF/controller.v
`timescale 1ns/1ps
module controller (ldA,ldB,sel_in,sel1,sel2,start,done,lt,gt,eq,clk);
    input start,lt,gt,eq,clk;
    output reg done,ldA,ldB,sel_in,sel1,sel2;
    reg [2:0] state;
    parameter S0 = 3'b001, S1 = 3'b010, S2 = 3'b011, S3 = 3'b100, S4 = 3'b101;

    always @(posedge clk) begin
        #1  case (state)
            S0 : if (start) state <= S1;
            S1 : state <= S2;
            S2 : if (lt) state <= S2;
            else if(gt) state <= S3;
            else if(eq) state <= S4;
            S3 : if (lt) state <= S2;
            else if(gt) state <= S3;
            else if(eq) state <= S4;
            S4 : state <= S4;
            default: state <= S0;
        endcase
    end

    always @(state) begin
        case (state)
            S0 : begin #1 sel_in =1;ldA =1 ;end
            S1 : begin #1 ldA =0; ldB =1;end
            S2 : begin #1 sel_in =0; ldA =0; sel1 =0; sel2 =1;end
            S3 : begin #1 sel1 =1; sel2 =0; ldA =1; ldB =0;end
            S4 : begin #1 sel_in =0; done =1; ldA =0; ldB =0;end
            default: begin state <= S0;end
        endcase
    end

endmodule

Datapath_and_controller/HCF/SUB.v
`timescale 1ns/1ps
module SUBT (out,in1,in2);
    input [15:0] in1,in2;
    output reg [15:0]out;

    always @(*) begin
        out = in1 - in2;
    end
endmodule

Datapath_and_controller/HCF/COMP.v
`timescale 1ns/1ps
module COMP (l,g,e,in1,in2);
    input [15:0] in1,in2;
    output l,g,e;

    assign l = in1 < in2;
    assign g = in1 > in2;
    assign e = in1 == in2;
endmodule

Datapath_and_controller/HCF/MUX2.v
`timescale 1ns/1ps
module MUX2 (out,in1,in2,sel2);
    input sel2;
    input [15:0] in1,in2;
    output [15:0] out;

    assign out = sel2 ? in1 : in2;
    
endmodule

Datapath_and_controller/HCF/MUX1.v
`timescale 1ns/1ps
module MUX1 (out,in1,in2,sel1);
    input sel1;
    input [15:0] in1,in2;
    output [15:0] out;

    assign out = sel1 ? in1 : in2;
    
endmodule

Datapath_and_controller/HCF/MUX_in.v
`timescale 1ns/1ps
module MUX_in (out,in1,in2,sel);
    input sel;
    input [15:0] in1,in2;
    output [15:0] out;

    assign out = sel ? in2 : in1;
    
endmodule

Datapath_and_controller/HCF/B.v
`timescale 1ns/1ps
module PIPO2 (dout,din,ld,clk);
    input ld,clk;
    input [15:0] din;
    output reg [15:0] dout;
    
    always @(posedge clk) begin
        if (ld) begin
            dout <= din;
        end
    end
endmodule

Datapath_and_controller/HCF/A.v
`timescale 1ns/1ps
module PIPO1 (dout,din,ld,clk);
    input ld,clk;
    input [15:0] din;
    output reg [15:0] dout;
    always @(posedge clk) begin
        if (ld) begin
            dout <= din;
        end
    end
endmodule

Datapath_and_controller/HCF/datapath.v
`timescale 1ns/1ps
module HCF (Sub_out,d_in,ldA,ldB,sel_in,sel1,sel2,lt,gt,eq,clk);
    input clk,ldA,ldB,sel_in,sel1,sel2;
    input [15:0] d_in;
    output [15:0] Sub_out;
    output lt,gt,eq;
    wire [15:0] Aout,Bout,Bus_in,X,Y;

    PIPO1 A(Aout,Bus_in,ldA,clk);
    PIPO2 B(Bout,Bus_in,ldB,clk);
    MUX_in Min(Bus_in,Sub_out,d_in,sel_in);
    MUX1 M1(X,Aout,Bout,sel1);
    MUX2 M2(Y,Aout,Bout,sel2);
    COMP CMP(lt,gt,eq,Aout,Bout);
    SUBT SBT(Sub_out,X,Y);

endmodule

Datapath_and_controller/HCF/hcf_test.v
`timescale 1ns/1ps
module DUT;

reg [15:0] d_in;
reg clk,start;
wire [15:0] Sub_out;
wire ldA,ldB,sel_in,sel1,sel2,lt,gt,eq,done;


HCF H1(Sub_out,d_in,ldA,ldB,sel_in,sel1,sel2,lt,gt,eq,clk);
controller C1(ldA,ldB,sel_in,sel1,sel2,start,done,lt,gt,eq,clk);
    
   initial begin
    clk = 1'b0;
    #3 start = 1'b1;
    #500 $finish;
   end 

   always #5 clk = ~clk;

   initial begin
    #4 d_in = 2;
    #12 d_in = 5;
   end

   initial 
begin
    $monitor("time=%0t done=%b", $time, done);
    $dumpfile ("hcf.vcd"); $dumpvars (0, DUT);
end

endmodule

Datapath_and_controller/HCF/hcf.vcd
$date
	Tue Mar 17 22:09:25 2026
$end
$version
	Icarus Verilog
$end
$timescale
	1ps
$end
$scope module DUT $end
$var wire 16 ! Sub_out [15:0] $end
$var wire 1 " done $end
$var wire 1 # eq $end
$var wire 1 $ gt $end
$var wire 1 % ldA $end
$var wire 1 & ldB $end
$var wire 1 ' lt $end
$var wire 1 ( sel1 $end
$var wire 1 ) sel2 $end
$var wire 1 * sel_in $end
$var reg 1 + clk $end
$var reg 16 , d_in [15:0] $end
$var reg 1 - start $end
$scope module H1 $end
$var wire 16 . Aout [15:0] $end
$var wire 16 / Bout [15:0] $end
$var wire 16 0 Bus_in [15:0] $end
$var wire 16 1 Sub_out [15:0] $end
$var wire 16 2 X [15:0] $end
$var wire 16 3 Y [15:0] $end
$var wire 1 4 clk $end
$var wire 16 5 d_in [15:0] $end
$var wire 1 # eq $end
$var wire 1 $ gt $end
$var wire 1 % ldA $end
$var wire 1 & ldB $end
$var wire 1 ' lt $end
$var wire 1 ( sel1 $end
$var wire 1 ) sel2 $end
$var wire 1 * sel_in $end
$scope module A $end
$var wire 1 4 clk $end
$var wire 16 6 din [15:0] $end
$var wire 1 % ld $end
$var reg 16 7 dout [15:0] $end
$upscope $end
$scope module B $end
$var wire 1 4 clk $end
$var wire 16 8 din [15:0] $end
$var wire 1 & ld $end
$var reg 16 9 dout [15:0] $end
$upscope $end
$scope module Min $end
$var wire 16 : in1 [15:0] $end
$var wire 16 ; in2 [15:0] $end
$var wire 16 < out [15:0] $end
$var wire 1 * sel $end
$upscope $end
$scope module M1 $end
$var wire 16 = in1 [15:0] $end
$var wire 16 > in2 [15:0] $end
$var wire 16 ? out [15:0] $end
$var wire 1 ( sel1 $end
$upscope $end
$scope module M2 $end
$var wire 16 @ in1 [15:0] $end
$var wire 16 A in2 [15:0] $end
$var wire 16 B out [15:0] $end
$var wire 1 ) sel2 $end
$upscope $end
$scope module CMP $end
$var wire 1 # e $end
$var wire 1 $ g $end
$var wire 16 C in1 [15:0] $end
$var wire 16 D in2 [15:0] $end
$var wire 1 ' l $end
$upscope $end
$scope module SBT $end
$var wire 16 E in1 [15:0] $end
$var wire 16 F in2 [15:0] $end
$var reg 16 G out [15:0] $end
$upscope $end
$upscope $end
$scope module C1 $end
$var wire 1 4 clk $end
$var wire 1 # eq $end
$var wire 1 $ gt $end
$var wire 1 ' lt $end
$var wire 1 H start $end
$var reg 1 I done $end
$var reg 1 J ldA $end
$var reg 1 K ldB $end
$var reg 1 L sel1 $end
$var reg 1 M sel2 $end
$var reg 1 N sel_in $end
$var reg 3 O state [2:0] $end
$upscope $end
$upscope $end
$enddefinitions $end
#0
$dumpvars
bx O
xN
xM
xL
xK
xJ
xI
xH
bx G
bx F
bx E
bx D
bx C
bx B
bx A
bx @
bx ?
bx >
bx =
bx <
bx ;
bx :
bx 9
bx 8
bx 7
bx 6
bx 5
04
bx 3
bx 2
bx 1
bx 0
bx /
bx .
x-
bx ,
0+
x*
x)
x(
x'
x&
x%
x$
x#
x"
bx !
$end
#3000
1-
1H
#4000
b10 ,
b10 5
b10 ;
#5000
1+
14
#6000
b1 O
#7000
b10 0
b10 6
b10 8
b10 <
1J
1%
1N
1*
#10000
0+
04
#15000
b10 7
b10 .
b10 =
b10 @
b10 C
1+
14
#16000
b10 O
b101 0
b101 6
b101 8
b101 <
b101 ,
b101 5
b101 ;
#17000
1K
1&
0J
0%
#20000
0+
04
#25000
b0xxx 2
b0xxx ?
b0xxx E
b0xxx 3
b0xxx B
b0xxx F
b101 9
1'
0$
0#
b101 /
b101 >
b101 A
b101 D
1+
14
#26000
b11 O
#27000
b11 G
b11 !
b11 1
b11 :
b10 3
b10 B
b10 F
b101 2
b101 ?
b101 E
b11 0
b11 6
b11 8
b11 <
1M
1)
0L
0(
0N
0*
#30000
0+
04
#35000
b1 0
b1 6
b1 8
b1 <
b1 G
b1 !
b1 1
b1 :
b11 2
b11 ?
b11 E
b11 9
b11 /
b11 >
b11 A
b11 D
1+
14
#40000
0+
04
#45000
b1111111111111111 0
b1111111111111111 6
b1111111111111111 8
b1111111111111111 <
b1111111111111111 G
b1111111111111111 !
b1111111111111111 1
b1111111111111111 :
b1 2
b1 ?
b1 E
b1 9
0'
1$
b1 /
b1 >
b1 A
b1 D
1+
14
#46000
b100 O
#47000
b1 0
b1 6
b1 8
b1 <
b1 G
b1 !
b1 1
b1 :
b1 3
b1 B
b1 F
b10 2
b10 ?
b10 E
0K
0&
1J
1%
0M
0)
1L
1(
#50000
0+
04
#55000
b0 0
b0 6
b0 8
b0 <
b0 G
b0 !
b0 1
b0 :
b1 2
b1 ?
b1 E
b1 7
0$
1#
b1 .
b1 =
b1 @
b1 C
1+
14
#56000
b101 O
#57000
0J
0%
1I
1"
