basics/taskandfunction/Tsk.v
`timescale 1ns/1ps
module adder (sum,cout,a,b,cin);
    input a,b,cin;
    output reg sum,cout;

    always @(cin or a or b) begin
        FA (sum,cout,a,b,cin);
    end

    task FA;
        output sum,carry;
        input A, B, C;
        begin
            #2 sum = A ^ B ^ C;
            carry = ((A&B) | (B&C) | (A&C));
        end
    endtask
endmodule

basics/taskandfunction/Ftest.v
`timescale 1ns/1ps
module DUT;
    reg a, b, cin;
    wire sum,cout;

    adder A1(sum,cout,a,b,cin);

    initial begin
        #50 $finish;
    end

    initial begin
        #0 a = 1'b0; b = 1'b0; cin = 1'b0;
        #5 a = 1'b0; b = 1'b0; cin = 1'b1;
        #5 a = 1'b0; b = 1'b1; cin = 1'b0;
        #5 a = 1'b0; b = 1'b1; cin = 1'b1;
        #5 a = 1'b1; b = 1'b0; cin = 1'b0;
        #5 a = 1'b1; b = 1'b0; cin = 1'b1;
        #5 a = 1'b1; b = 1'b1; cin = 1'b0;
        #5 a = 1'b1; b = 1'b1; cin = 1'b1;
    end

    initial begin
        $monitor ("time=0%t sum=%b cout=%b",$time , sum, cout);
        $dumpvars(0,DUT); $dumpfile("dump.vcd");
    end
endmodule

basics/taskandfunction/dump.vcd
$date
	Tue Mar 31 14:23:26 2026
$end
$version
	Icarus Verilog
$end
$timescale
	1ps
$end
$scope module DUT $end
$var wire 1 ! cout $end
$var wire 1 " sum $end
$var reg 1 # a $end
$var reg 1 $ b $end
$var reg 1 % cin $end
$scope module A1 $end
$var wire 1 & a $end
$var wire 1 ' b $end
$var wire 1 ( cin $end
$var reg 1 ) cout $end
$var reg 1 * sum $end
$scope task FA $end
$var reg 1 + A $end
$var reg 1 , B $end
$var reg 1 - C $end
$var reg 1 . carry $end
$var reg 1 / sum $end
$upscope $end
$upscope $end
$upscope $end
$enddefinitions $end
#0
$dumpvars
x/
x.
0-
0,
0+
x*
x)
0(
0'
0&
0%
0$
0#
x"
x!
$end
#2000
0)
0!
0*
0"
0.
0/
#5000
1-
1%
1(
#7000
1*
1"
1/
#10000
0-
1,
0%
0(
1$
1'
#15000
1-
1%
1(
#17000
1)
1!
0*
0"
1.
0/
#20000
0-
0,
1+
0%
0(
0$
0'
1#
1&
#22000
0)
0!
1*
1"
0.
1/
#25000
1-
1%
1(
#27000
1)
1!
0*
0"
1.
0/
#30000
0-
1,
0%
0(
1$
1'
#35000
1-
1%
1(
#37000
1*
1"
1/
