basics/3bitup/3bitup.v
`timescale 1ns/1ps
module cntr (start,clk,rst,cnt);
    input start,clk,rst;
    output reg [2:0] cnt;
    wire [2:0] next_cnt;

    assign next_cnt = cnt + 1'b1;

    always @(posedge clk or negedge rst)
    begin
        if (!rst) 
        begin
            cnt <= 3'd0;
        end
        else if(start)
        begin
            cnt <= next_cnt;
        end
    end
endmodule

basics/3bitup/3bittest.v
`timescale 1ns/1ps
module DUT;
    reg start,clk,rst;
    wire [2:0] cnt;

    cntr C1(start,clk,rst,cnt);

    initial 
    begin
    rst = 1'b0;
    clk = 1'b0;
    #200 $finish;
    end

    always #5 clk = ~clk;

    initial begin
       #10 rst = 1'b1; start = 1'b1;
    end

    initial 
    begin
        $monitor("time=0%t cnt = %d", $time, cnt);
        $dumpvars(0,DUT); $dumpfile("3bit.vcd");
    end
endmodule

basics/3bitup/dump.vcd
$date
	Sat Mar 28 19:23:12 2026
$end
$version
	Icarus Verilog
$end
$timescale
	1ps
$end
$scope module DUT $end
$var wire 3 ! cnt [2:0] $end
$var reg 1 " clk $end
$var reg 1 # rst $end
$var reg 1 $ start $end
$scope module C1 $end
$var wire 1 % clk $end
$var wire 3 & next_cnt [2:0] $end
$var wire 1 ' rst $end
$var wire 1 ( start $end
$var reg 3 ) cnt [2:0] $end
$upscope $end
$upscope $end
$enddefinitions $end
#0
$dumpvars
b0 )
x(
0'
b1 &
0%
x$
0#
0"
b0 !
$end
#5000
1"
1%
#10000
0"
0%
1$
1(
1#
1'
#15000
b1 )
b10 &
b1 !
1"
1%
#20000
0"
0%
#25000
b10 )
b11 &
b10 !
1"
1%
#30000
0"
0%
#35000
b11 )
b100 &
b11 !
1"
1%
#40000
0"
0%
#45000
b100 )
b101 &
b100 !
1"
1%
#50000
0"
0%
#55000
b101 )
b110 &
b101 !
1"
1%
#60000
0"
0%
#65000
b110 )
b111 &
b110 !
1"
1%
#70000
0"
0%
#75000
b111 )
b0 &
b111 !
1"
1%
#80000
0"
0%
#85000
b0 )
b1 &
b0 !
1"
1%
#90000
0"
0%
#95000
b1 )
b10 &
b1 !
1"
1%
#100000
0"
0%
#105000
b10 )
b11 &
b10 !
1"
1%
#110000
0"
0%
#115000
b11 )
b100 &
b11 !
1"
1%
#120000
0"
0%
#125000
b100 )
b101 &
b100 !
1"
1%
#130000
0"
0%
#135000
b101 )
b110 &
b101 !
1"
1%
#140000
0"
0%
#145000
b110 )
b111 &
b110 !
1"
1%
#150000
0"
0%
#155000
b111 )
b0 &
b111 !
1"
1%
#160000
0"
0%
#165000
b0 )
b1 &
b0 !
1"
1%
#170000
0"
0%
#175000
b1 )
b10 &
b1 !
1"
1%
#180000
0"
0%
#185000
b10 )
b11 &
b10 !
1"
1%
#190000
0"
0%
#195000
b11 )
b100 &
b11 !
1"
1%
