FIFO/Synchronous_fifo/fifosync.v
`timescale 1ns/1ps

module FIFOSYNC (
    cs,
    wr_en,
    rd_en,
    clk,
    rst,
    data_in,
    full,
    empty,
    data_out
);

    parameter FIFO_DEPTH    = 8;
    parameter DATA_WIDTH    = 32;
    parameter FIFO_DEPTHLOG = $clog2(FIFO_DEPTH);

    input cs;
    input wr_en;
    input rd_en;
    input clk;
    input rst;

    input [DATA_WIDTH-1:0] data_in;

    output full;
    output empty;

    output reg [DATA_WIDTH-1:0] data_out;

    reg [DATA_WIDTH-1:0] fifo [FIFO_DEPTH-1:0];

    reg [FIFO_DEPTHLOG:0] wr_addr;
    reg [FIFO_DEPTHLOG:0] rd_addr;

    // FIFO EMPTY
    assign empty = (wr_addr == rd_addr);

    // FIFO FULL
    assign full = (wr_addr[FIFO_DEPTHLOG] == 
                   ~rd_addr[FIFO_DEPTHLOG]) &&
                  (wr_addr[FIFO_DEPTHLOG-1:0] == 
                   rd_addr[FIFO_DEPTHLOG-1:0]);

    // WRITE
    always @(posedge clk or negedge rst) begin
        if (!rst) begin
            wr_addr <= 0;
        end
        else if (cs && wr_en && !full) begin
            fifo[wr_addr[FIFO_DEPTHLOG-1:0]] <= data_in;
            wr_addr <= wr_addr + 1'b1;
        end
    end

    // READ
    always @(posedge clk or negedge rst) begin
        if (!rst) begin
            rd_addr  <= 0;
            data_out <= 0;
        end
        else if (cs && rd_en && !empty) begin
            data_out <= fifo[rd_addr[FIFO_DEPTHLOG-1:0]];
            rd_addr <= rd_addr + 1'b1;
        end
    end

endmodule

FIFO/Synchronous_fifo/fifosyntest.v
`timescale 1ns/1ps
module DUT;

parameter FIFO_DEPTH = 8;
parameter DATA_WIDTH = 32;
parameter FIFOHALF = 4;
reg clk,rd_en,wr_en,rst,cs;
reg [DATA_WIDTH-1:0] data_in;
wire [DATA_WIDTH-1:0] data_out;
wire empty,full;
integer k;

FIFOSYNC F1(cs,wr_en,rd_en,clk,rst,data_in,full,empty,data_out);

always #5 clk = ~clk;
initial begin
        clk =0;
        rst =0;
        cs=0;

        rd_en=0;
        wr_en=0;
        $display("Scenario1 checking empty port");
        $display("______________________________");
        //scenario1--------------------------------------------------------------------------
        #2
        $display("time : %d, Empty : %d", $time , empty); //checking empty port

        #10 rst =1;

        $display("================================");
        //scenario2--------------------------------------------------------------------------------
        $display("Scenario2 checking full port port");
        $display("______________________________");
        data_in = 0;
        wr_en = 1;
        cs = 1;

        for (k = 0; k < FIFO_DEPTH; k = k + 1) begin

            data_in = k * 2;

            @(posedge clk);
            #1;

            $display("Time = %0t, FIFO[%0d] = %0d",
                    $time, k, F1.fifo[k]);

        end

        wr_en = 0;

        #1;

        $display("FULL  = %0d", full);
        $display("EMPTY = %0d", empty);
        $display("================================");

        //scenario3-------------------------------------------------------------------------
        $display("Scenario3 Writing after full stack (it doesn't write until read occurs)");
        $display("______________________________________________________________________");

        @(posedge clk)
        wr_en =1;
        $display("================================");
        repeat(2)
        begin
        @(posedge clk)
            data_in = k*3;// writing after full
            $display("Time : %d , FIFOvalue : %d", $time , F1.fifo[0]);
        end
        $display("================================");
        wr_en =0;
        #1 
        rst =0;
        #1
        rst =1;
        //scenario4-------------------------------------------------------------------------
        $display("Scenario4 Writing upto 3 stack and then reading upto 3 stack");
        $display("____________________________________________________________");
        data_in = 0;// first loading data
        wr_en=1;
        for (k = 0; k<FIFOHALF-1; k = k+1) 
        begin
            data_in =  k*4;
            @(posedge clk)
            #1; // necessary so that data load in the fifo and then will watch it in terminal
            $display("Time = %0t, FIFO[%0d] = %0d",
            $time, k, F1.fifo[k]);
        end
        @(posedge clk)
        rd_en =1;// after 3rd clk edge empty should be high and automatically read should
        wr_en =0;// stop and last data out will be 8
        #1
       for (k = 0; k < 3; k = k + 1) begin
            $display("Time : %0t, dataout[%0d] = %0d",
                    $time, k, data_out);
            @(posedge clk);
            #1;
        end
        @(posedge clk)
        $display("FULL  = %0d", full);
        $display("EMPTY = %0d", empty);
        rd_en = 0;
        $display("================================");
        #20 $finish;
end
initial begin
    $dumpfile("dump.vcd");
    $dumpvars(0,DUT);
end

endmodule

FIFO/Synchronous_fifo/dump.vcd
$date
	Sat Aug 22 00:21:30 2026
$end
$version
	Icarus Verilog
$end
$timescale
	1ps
$end
$scope module DUT $end
$var wire 32 ! data_out [31:0] $end
$var wire 1 " empty $end
$var wire 1 # full $end
$var reg 1 $ clk $end
$var reg 1 % cs $end
$var reg 32 & data_in [31:0] $end
$var integer 32 ' k [31:0] $end
$var reg 1 ( rd_en $end
$var reg 1 ) rst $end
$var reg 1 * wr_en $end
$scope module F1 $end
$var wire 1 + clk $end
$var wire 1 , cs $end
$var wire 32 - data_in [31:0] $end
$var wire 1 " empty $end
$var wire 1 # full $end
$var wire 1 . rd_en $end
$var wire 1 / rst $end
$var wire 1 0 wr_en $end
$var reg 32 1 data_out [31:0] $end
$var reg 4 2 rd_addr [3:0] $end
$var reg 4 3 wr_addr [3:0] $end
$upscope $end
$upscope $end
$enddefinitions $end
#0
$dumpvars
b0 3
b0 2
b0 1
00
0/
0.
bx -
0,
0+
0*
0)
0(
bx '
bx &
0%
0$
0#
1"
b0 !
$end
#5000
1$
1+
#10000
0$
0+
#12000
b0 '
1%
1,
1*
10
b0 &
b0 -
1)
1/
#15000
b1 3
0"
1$
1+
#16000
b10 &
b10 -
b1 '
#20000
0$
0+
#25000
b10 3
1$
1+
#26000
b100 &
b100 -
b10 '
#30000
0$
0+
#35000
b11 3
1$
1+
#36000
b110 &
b110 -
b11 '
#40000
0$
0+
#45000
b100 3
1$
1+
#46000
b1000 &
b1000 -
b100 '
#50000
0$
0+
#55000
b101 3
1$
1+
#56000
b1010 &
b1010 -
b101 '
#60000
0$
0+
#65000
b110 3
1$
1+
#66000
b1100 &
b1100 -
b110 '
#70000
0$
0+
#75000
b111 3
1$
1+
#76000
b1110 &
b1110 -
b111 '
#80000
0$
0+
#85000
1#
b1000 3
1$
1+
#86000
0*
00
b1000 '
#90000
0$
0+
#95000
1*
10
1$
1+
#100000
0$
0+
#105000
b11000 &
b11000 -
1$
1+
#110000
0$
0+
#115000
0*
00
1$
1+
#116000
0#
b0 3
1"
0)
0/
#117000
b0 '
1*
10
b0 &
b0 -
1)
1/
#120000
0$
0+
#125000
b1 3
0"
1$
1+
#126000
b100 &
b100 -
b1 '
#130000
0$
0+
#135000
b10 3
1$
1+
#136000
b1000 &
b1000 -
b10 '
#140000
0$
0+
#145000
b11 3
1$
1+
#146000
b11 '
#150000
0$
0+
#155000
b1 2
0*
00
1(
1.
1$
1+
#156000
b0 '
#160000
0$
0+
#165000
b10 2
b100 1
b100 !
1$
1+
#166000
b1 '
#170000
0$
0+
#175000
b11 2
1"
b1000 1
b1000 !
1$
1+
#176000
b10 '
#180000
0$
0+
#185000
1$
1+
#186000
b11 '
#190000
0$
0+
#195000
0(
0.
1$
1+
