Datapath_and_controller/boothmultiplier/controller.v
`timescale 1ns/1ps
module controller (start,count,ldA,clrA,sftA,ldQ,sftQ,clrQ,decr,ldcnt,clk,clrff,Q0,ldM,qm1,addsub,done);
    input clk, Q0;
    input [4:0] count;
    input start,qm1;
    output reg ldA,clrA,sftA,ldQ,sftQ,clrQ,decr,ldcnt,clrff,ldM,addsub,done;
    reg [2:0] state;
    parameter S0 = 3'b000, S1 =3'b001, S2 =3'b010, S3 =3'b011, S4 =3'b100, S5 =3'b101, S6 =3'b110, S7 =3'b111;
    
    always @(posedge clk) begin
        case (state)
            S0 : if (start) state <= S1;
            S1 : state <= S2;
            S2 : state <= S3;
            S3 : if (count == 0) state <= S7; 
                else if ({Q0,qm1} == 2'b10) state <= S4; 
                else if ({Q0,qm1} == 2'b01) state <= S5; 
                else if (Q0 == qm1) state <= S6; 
            S4 : state <= S6;
            S5 : state <= S6;
            S6 : state <= S3;
            S7 : state <= S7;
            default: state <= S0;
        endcase
    end

//count,ldA,clrA,sftA,ldQ,sftQ,clrQ,decr,ldcnt,clk,clrff,Q[0],ldM,addsub,done
    always @(state) begin
        case (state)
            S0 : begin
               #1 clrA =1; clrff =1; ldM =1; clrQ =1; ldcnt =1;
            end
            S1 : begin
                #1 clrQ =0; clrA =0; clrff =0; ldM =0; ldQ =1; ldcnt =0 ;     
            end 
            S2 : begin
                #1 decr =0; ldQ =0; sftA =0; sftQ =0;
            end 
            S3 : begin
                #1 decr =0; sftA =0; sftQ =0;
            end 
            S4 : begin
                #1 decr =0; addsub =0; ldA =1; sftA =0; sftQ =0;    
            end 
            S5 : begin
                #1 decr =0; addsub =1; ldA =1; sftA =0; sftQ =0;
            end 
            S6 : begin
                #1 decr =1; ldA =0; sftA =1; sftQ =1;    
            end 
            S7 : begin
                #1 done =1;    
            end 
            default: state <= S0;
        endcase
    end
endmodule

Datapath_and_controller/keyconcept/DFF.v
`timescale 1ns/1ps
module DFF (dout,din,clr,clk);
    input din,clr,clk;
    output reg dout;

    always @(posedge clk) begin
        if (clr) begin
            dout <= 1'b0;
        end else begin
            dout <= din;
        end
    end
endmodule

Datapath_and_controller/boothmultiplier/ALU.v
`timescale 1ns/1ps
module ALU (out,in1,in2,as);
    input [4:0] in1,in2;
    input as;
    output reg [4:0] out;
    
    always @(*) begin
        if (as == 1) begin
            out = in1 + in2;
        end else if (as == 0) begin
            out = in1 - in2;
        end
    end
endmodule

Datapath_and_controller/boothmultiplier/M.v
`timescale 1ns/1ps
module PIPO (dout,din,ld,clk);
    input [4:0] din;
    input ld,clk;
    output reg [4:0] dout;

    always @(posedge clk) begin
        if (ld) begin
            dout <= din;
        end
    end
endmodule

Datapath_and_controller/boothmultiplier/cntr.v
`timescale 1ns/1ps
module CNTR (dout,ld,dec,clk);
    input ld,dec,clk;
    output reg [4:0] dout;

    always @(posedge clk) begin
        if (ld) begin
            dout <= 5'b00101;
        end else if(dec) begin
            dout <= dout - 1;
        end
    end
endmodule

Datapath_and_controller/boothmultiplier/shiftreg.v
`timescale 1ns/1ps
module shiftreg (dout,din,in1,ld,clr,sft,clk);
    input [4:0] din;
    input in1,ld,clr,sft,clk;
    output reg [4:0] dout;

    always @(posedge clk) begin
        if (clr) begin
            dout <= 5'b0;
        end
        else if (ld) begin
            dout <= din;
        end
        else if (sft) begin
            dout <= {in1,dout[4:1]};
        end
    end
endmodule

Datapath_and_controller/boothmultiplier/out.v
`timescale 1ns/1ps
module out (out,in1,in2);
    input [4:0] in1 , in2;
    output [7:0] out;

    assign out = {in1,in2};
endmodule

Datapath_and_controller/boothmultiplier/datapath.v
`timescale 1ns/1ps
module BM (ldA,clrA,sftA,ldQ,sftQ,clrQ,decr,ldcnt,data_in,clk,qm1,Q0,clrff,ldM,addsub,count,MUL);
    input [4:0] data_in;
    input ldA,clrA,sftA,ldQ,sftQ,clrQ,decr,ldcnt,clrff,ldM,addsub,clk; 
    output qm1,Q0;
    output [7:0] MUL;
    wire [4:0] A,M,Z,Q;
    output [4:0] count;
    assign Q0 = Q[0];

    out ot(MUL,A[4:0],Q[4:0]);
    shiftreg AR(A,Z,A[4],ldA,clrA,sftA,clk);
    shiftreg QL(Q,data_in,A[0],ldQ,clrQ,sftQ,clk);
    CNTR CNT(count,ldcnt,decr,clk);
    PIPO ML(M,data_in,ldM,clk);
    ALU ADSB(Z,A,M,addsub);
    DFF dff(qm1,Q[0],clrff,clk);


endmodule

Datapath_and_controller/boothmultiplier/boothtest.v
module DUT;

    reg clk,start;
    reg [4:0] data_in;
    wire done,Q0,ldA,clrA,sftA,ldQ,sftQ,clrQ,decr,ldcnt,qm1,clrff,ldM,addsub;
    wire [4:0] count;
    wire [7:0] MUL;

    BM B1(ldA,clrA,sftA,ldQ,sftQ,clrQ,decr,ldcnt,data_in,clk,qm1,Q0,clrff,ldM,addsub,count,MUL);
    controller C1(start,count,ldA,clrA,sftA,ldQ,sftQ,clrQ,decr,ldcnt,clk,clrff,Q0,ldM,qm1,addsub,done);

    initial begin
        clk = 1'b0;
        #3 start = 1'b1;
        #500 $finish;
    end

    always #5 clk = ~clk;

    initial begin
        #14 data_in = 11;
        #10 data_in = 6;
    end

    initial begin
        $monitor ("time=%0t done=%b " , $time , done);
        $dumpfile("booth.vcd") ; $dumpvars(0,DUT);
    end
endmodule

Datapath_and_controller/boothmultiplier/booth.vcd
$date
	Sat Mar 28 17:14:43 2026
$end
$version
	Icarus Verilog
$end
$timescale
	1ps
$end
$scope module DUT $end
$var wire 8 ! MUL [7:0] $end
$var wire 1 " Q0 $end
$var wire 1 # addsub $end
$var wire 1 $ clrA $end
$var wire 1 % clrQ $end
$var wire 1 & clrff $end
$var wire 5 ' count [4:0] $end
$var wire 1 ( decr $end
$var wire 1 ) done $end
$var wire 1 * ldA $end
$var wire 1 + ldM $end
$var wire 1 , ldQ $end
$var wire 1 - ldcnt $end
$var wire 1 . qm1 $end
$var wire 1 / sftA $end
$var wire 1 0 sftQ $end
$var reg 1 1 clk $end
$var reg 5 2 data_in [4:0] $end
$var reg 1 3 start $end
$scope module B1 $end
$var wire 5 4 A [4:0] $end
$var wire 5 5 M [4:0] $end
$var wire 8 6 MUL [7:0] $end
$var wire 5 7 Q [4:0] $end
$var wire 1 " Q0 $end
$var wire 5 8 Z [4:0] $end
$var wire 1 # addsub $end
$var wire 1 9 clk $end
$var wire 1 $ clrA $end
$var wire 1 % clrQ $end
$var wire 1 & clrff $end
$var wire 5 : count [4:0] $end
$var wire 5 ; data_in [4:0] $end
$var wire 1 ( decr $end
$var wire 1 * ldA $end
$var wire 1 + ldM $end
$var wire 1 , ldQ $end
$var wire 1 - ldcnt $end
$var wire 1 . qm1 $end
$var wire 1 / sftA $end
$var wire 1 0 sftQ $end
$scope module ot $end
$var wire 5 < in1 [4:0] $end
$var wire 5 = in2 [4:0] $end
$var wire 8 > out [7:0] $end
$upscope $end
$scope module AR $end
$var wire 1 9 clk $end
$var wire 1 $ clr $end
$var wire 5 ? din [4:0] $end
$var wire 1 @ in1 $end
$var wire 1 * ld $end
$var wire 1 / sft $end
$var reg 5 A dout [4:0] $end
$upscope $end
$scope module QL $end
$var wire 1 9 clk $end
$var wire 1 % clr $end
$var wire 5 B din [4:0] $end
$var wire 1 C in1 $end
$var wire 1 , ld $end
$var wire 1 0 sft $end
$var reg 5 D dout [4:0] $end
$upscope $end
$scope module CNT $end
$var wire 1 9 clk $end
$var wire 1 ( dec $end
$var wire 1 - ld $end
$var reg 5 E dout [4:0] $end
$upscope $end
$scope module ML $end
$var wire 1 9 clk $end
$var wire 5 F din [4:0] $end
$var wire 1 + ld $end
$var reg 5 G dout [4:0] $end
$upscope $end
$scope module ADSB $end
$var wire 1 # as $end
$var wire 5 H in1 [4:0] $end
$var wire 5 I in2 [4:0] $end
$var reg 5 J out [4:0] $end
$upscope $end
$scope module dff $end
$var wire 1 9 clk $end
$var wire 1 & clr $end
$var wire 1 K din $end
$var reg 1 L dout $end
$upscope $end
$upscope $end
$scope module C1 $end
$var wire 1 " Q0 $end
$var wire 1 9 clk $end
$var wire 5 M count [4:0] $end
$var wire 1 . qm1 $end
$var wire 1 N start $end
$var reg 1 O addsub $end
$var reg 1 P clrA $end
$var reg 1 Q clrQ $end
$var reg 1 R clrff $end
$var reg 1 S decr $end
$var reg 1 T done $end
$var reg 1 U ldA $end
$var reg 1 V ldM $end
$var reg 1 W ldQ $end
$var reg 1 X ldcnt $end
$var reg 1 Y sftA $end
$var reg 1 Z sftQ $end
$var reg 3 [ state [2:0] $end
$upscope $end
$upscope $end
$enddefinitions $end
#0
$dumpvars
bx [
xZ
xY
xX
xW
xV
xU
xT
xS
xR
xQ
xP
xO
xN
bx M
xL
xK
bx J
bx I
bx H
bx G
bx F
bx E
bx D
xC
bx B
bx A
x@
bx ?
bx >
bx =
bx <
bx ;
bx :
09
bx 8
bx 7
bx 6
bx 5
bx 4
x3
bx 2
01
x0
x/
x.
x-
x,
x+
x*
x)
x(
bx '
x&
x%
x$
x#
x"
bx !
$end
#3000
13
1N
#5000
b0 [
11
19
#6000
1X
1-
1Q
1%
1V
1+
1R
1&
1P
1$
#10000
01
09
#14000
b1011 2
b1011 ;
b1011 B
b1011 F
#15000
0K
0"
b0 !
b0 6
b0 >
0C
0@
b1 [
0L
0.
b1011 G
b1011 5
b1011 I
b101 E
b101 '
b101 :
b101 M
b0 D
b0 7
b0 =
b0 A
b0 4
b0 <
b0 H
11
19
#16000
0X
0-
1W
1,
0V
0+
0R
0&
0P
0$
0Q
0%
#20000
01
09
#24000
b110 2
b110 ;
b110 B
b110 F
#25000
b110 !
b110 6
b110 >
b110 D
b110 7
b110 =
b10 [
11
19
#26000
0Z
00
0Y
0/
0W
0,
0S
0(
#30000
01
09
#35000
b11 [
11
19
#40000
01
09
#45000
b110 [
11
19
#46000
1Z
10
1Y
1/
0U
0*
1S
1(
#50000
01
09
#55000
b11 !
b11 6
b11 >
1K
1"
b11 [
b100 E
b100 '
b100 :
b100 M
b11 D
b11 7
b11 =
11
19
#56000
0Z
00
0Y
0/
0S
0(
#60000
01
09
#65000
1L
1.
b100 [
11
19
#66000
b10101 J
b10101 8
b10101 ?
1U
1*
0O
0#
#70000
01
09
#75000
b10100011 !
b10100011 6
b10100011 >
1C
1@
b1010 J
b1010 8
b1010 ?
b110 [
b10101 A
b10101 4
b10101 <
b10101 H
11
19
#76000
1Z
10
1Y
1/
0U
0*
1S
1(
#80000
01
09
#85000
0C
b1111 J
b1111 8
b1111 ?
b1010001 !
b1010001 6
b1010001 >
b11010 A
b11010 4
b11010 <
b11010 H
b10001 D
b10001 7
b10001 =
b11 E
b11 '
b11 :
b11 M
b11 [
11
19
#86000
0Z
00
0Y
0/
0S
0(
#90000
01
09
#95000
b110 [
11
19
#96000
1Z
10
1Y
1/
1S
1(
#100000
01
09
#105000
1C
b10010 J
b10010 8
b10010 ?
b10101000 !
b10101000 6
b10101000 >
0K
0"
b11101 A
b11101 4
b11101 <
b11101 H
b1000 D
b1000 7
b1000 =
b10 E
b10 '
b10 :
b10 M
b11 [
11
19
#106000
0Z
00
0Y
0/
0S
0(
#110000
01
09
#115000
b101 [
0L
0.
11
19
#116000
b1000 J
b1000 8
b1000 ?
1U
1*
1O
1#
#120000
01
09
#125000
b1000 !
b1000 6
b1000 >
0C
0@
b10011 J
b10011 8
b10011 ?
b1000 A
b1000 4
b1000 <
b1000 H
b110 [
11
19
#126000
1Z
10
1Y
1/
0U
0*
1S
1(
#130000
01
09
#135000
b10000100 !
b10000100 6
b10000100 >
b1111 J
b1111 8
b1111 ?
b11 [
b1 E
b1 '
b1 :
b1 M
b100 D
b100 7
b100 =
b100 A
b100 4
b100 <
b100 H
11
19
#136000
0Z
00
0Y
0/
0S
0(
#140000
01
09
#145000
b110 [
11
19
#146000
1Z
10
1Y
1/
1S
1(
#150000
01
09
#155000
b1000010 !
b1000010 6
b1000010 >
b1101 J
b1101 8
b1101 ?
b11 [
b0 E
b0 '
b0 :
b0 M
b10 D
b10 7
b10 =
b10 A
b10 4
b10 <
b10 H
11
19
#156000
0Z
00
0Y
0/
0S
0(
#160000
01
09
#165000
b111 [
11
19
#166000
1T
1)
