Datapath_and_controller/multiplier/controller.v
`timescale 1ns/1ps
module controller (ldA,ldP,clrP,ldB,decB,start,done,eqz,clk);
    input clk,eqz,start;
    output reg ldA,ldP,clrP,ldB,decB,done;

    reg [2:0] state;
    parameter S0 = 3'b001,S1 = 3'b010,S2 = 3'b011,S3 = 3'b100,S4 = 3'b101;
    always @(posedge clk) begin
        case (state)
            S0 : if(start) state <= S1;
            S1 : state <= S2;
            S2 : state <= S3;
            S3 : #2 if (eqz) state <= S4;
            S4 : state <= S4;
            default: state <= S0;
        endcase
    end

    always @(state) begin
        case (state)
            S0 : begin #1 ldA =1'b0; ldB =1'b0; decB =1'b0; ldP =1'b0; clrP=1'b0; done =1'b0; end
            S1 : begin #1 ldA =1'b1; end
            S2 : begin #1 ldA =1'b0; ldB =1'b1; clrP=1'b1; end
            S3 : begin #1 ldB =1'b0; clrP =1'b0; decB =1'b1; ldP =1'b1;ldA =1'b0; end
            S4 : begin #1 done =1'b1; ldP =1'b0; decB =1'b0; end
            default: begin #1 ldA =1'b0; ldB =1'b0; decB =1'b0; ldP =1'b0; clrP=1'b0; done =1'b0; end
        endcase
    end
endmodule

Datapath_and_controller/multiplier/EQZ.v
`timescale 1ns/1ps
module EQZ (eq,din);
    input [15:0] din;
    output eq;
    assign eq = (din == 1);
endmodule

Datapath_and_controller/multiplier/adder.v
`timescale 1ns/1ps
module ADD (out,in1,in2);
    input [15:0] in1;
    input [31:0] in2;
    output reg [31:0] out;
    always @(*) 
    begin
        out = in1 + in2;
    end
endmodule

Datapath_and_controller/multiplier/B.v
`timescale 1ns / 1ps
module CNTR (dout,din,ld,dec,clk);
    input ld,dec,clk;
    input [15:0] din;
    output reg [15:0] dout;
    always @(posedge clk) 
    begin
        if (ld) dout <= din;
        else if(dec) dout <= dout - 1;
    end
endmodule

Datapath_and_controller/multiplier/P.v
`timescale 1ns/1ps
module PIPO2 (dout,din,ld,clr,clk);
    input ld,clr,clk;
    input [31:0] din;
    output reg [31:0] dout;
    always @(posedge clk or posedge clr)
    begin
        if (clr) begin
            dout <= 32'b0;
        end else if (ld) begin
            dout <= din;
        end
    end
endmodule

Datapath_and_controller/multiplier/A.v
`timescale 1ns / 1ps
module PIPO1 (dout,din,ld,clk);
    input ld,clk;
    input [15:0] din;
    output reg [15:0] dout;
    always @(posedge clk)
     begin
        if (ld) 
        begin
            dout <= din;
        end
    end
endmodule

Datapath_and_controller/multiplier/multiplier.v
`timescale 1ns / 1ps
module datapath(data_in,ldA,ldP,clrP,ldB,decB,eqz,Mul,clk);
    input ldA,ldB,decB,ldP,clrP,clk;
    input [15:0] data_in;
    output eqz;
    output [31:0] Mul;
    wire [15:0] X,Bus_in,Bout;
    wire [31:0] Y,Z;
    assign Bus_in = data_in;
    assign Z = Mul;

    PIPO1 A(X,Bus_in,ldA,clk);
    PIPO2 P(Y,Mul,ldP,clrP,clk);
    CNTR B(Bout,Bus_in,ldB,decB,clk);
    ADD AD(Mul,X,Y);
    EQZ COMP(eqz,Bout);
endmodule

Datapath_and_controller/multiplier/mul_test.v
`timescale 1ns/1ps
module mul_test;

reg [15:0] data_in;
reg clk, start;
wire [31:0] Mul;
wire ldA,ldP,clrP,ldB,decB;
wire done,eqz;

datapath DP (data_in,ldA,ldP,clrP,ldB,decB,eqz,Mul,clk);
controller CON (ldA,ldP,clrP,ldB,decB,start,done,eqz,clk);

initial 
begin
    clk = 1'b0;
    #3 start = 1'b1;
    #97 $finish;
end

always #5 clk = ~clk;

initial 
begin
    #24 data_in = 17;
    #10 data_in = 5;
end
initial 
begin
    $monitor("time=%0t X=%d Y=%d Mul=%d done=%b", $time, DP.X, DP.Y, Mul, done);
    $dumpfile ("mul.vcd"); $dumpvars (0, mul_test);
end

endmodule

Datapath_and_controller/multiplier/mul.vcd
$date
	Sun Mar 15 16:21:39 2026
$end
$version
	Icarus Verilog
$end
$timescale
	1ps
$end
$scope module mul_test $end
$var wire 32 ! Mul [31:0] $end
$var wire 1 " clrP $end
$var wire 1 # decB $end
$var wire 1 $ done $end
$var wire 1 % eqz $end
$var wire 1 & ldA $end
$var wire 1 ' ldB $end
$var wire 1 ( ldP $end
$var reg 1 ) clk $end
$var reg 16 * data_in [15:0] $end
$var reg 1 + start $end
$scope module DP $end
$var wire 16 , Bout [15:0] $end
$var wire 16 - Bus_in [15:0] $end
$var wire 32 . Mul [31:0] $end
$var wire 16 / X [15:0] $end
$var wire 32 0 Y [31:0] $end
$var wire 32 1 Z [31:0] $end
$var wire 1 2 clk $end
$var wire 1 " clrP $end
$var wire 16 3 data_in [15:0] $end
$var wire 1 # decB $end
$var wire 1 % eqz $end
$var wire 1 & ldA $end
$var wire 1 ' ldB $end
$var wire 1 ( ldP $end
$scope module A $end
$var wire 1 2 clk $end
$var wire 16 4 din [15:0] $end
$var wire 1 & ld $end
$var reg 16 5 dout [15:0] $end
$upscope $end
$scope module P $end
$var wire 1 2 clk $end
$var wire 1 " clr $end
$var wire 32 6 din [31:0] $end
$var wire 1 ( ld $end
$var reg 32 7 dout [31:0] $end
$upscope $end
$scope module B $end
$var wire 1 2 clk $end
$var wire 1 # dec $end
$var wire 16 8 din [15:0] $end
$var wire 1 ' ld $end
$var reg 16 9 dout [15:0] $end
$upscope $end
$scope module AD $end
$var wire 16 : in1 [15:0] $end
$var wire 32 ; in2 [31:0] $end
$var reg 32 < out [31:0] $end
$upscope $end
$scope module COMP $end
$var wire 16 = din [15:0] $end
$var wire 1 % eq $end
$upscope $end
$upscope $end
$scope module CON $end
$var wire 1 2 clk $end
$var wire 1 % eqz $end
$var wire 1 > start $end
$var reg 1 ? clrP $end
$var reg 1 @ decB $end
$var reg 1 A done $end
$var reg 1 B ldA $end
$var reg 1 C ldB $end
$var reg 1 D ldP $end
$var reg 3 E state [2:0] $end
$upscope $end
$upscope $end
$enddefinitions $end
#0
$dumpvars
bx E
xD
xC
xB
xA
x@
x?
x>
bx =
bx <
bx ;
bx :
bx 9
bx 8
bx 7
bx 6
bx 5
bx 4
bx 3
02
bx 1
bx 0
bx /
bx .
bx -
bx ,
x+
bx *
0)
x(
x'
x&
x%
x$
x#
x"
bx !
$end
#3000
1+
1>
#5000
b1 E
1)
12
#6000
0A
0$
0?
0"
0D
0(
0@
0#
0C
0'
0B
0&
#10000
0)
02
#15000
b10 E
1)
12
#16000
1B
1&
#20000
0)
02
#24000
b10001 *
b10001 -
b10001 4
b10001 8
b10001 3
#25000
b10001 5
b10001 /
b10001 :
b11 E
1)
12
#26000
b10001 <
b10001 1
b10001 !
b10001 .
b10001 6
b0 7
b0 0
b0 ;
1?
1"
1C
1'
0B
0&
#30000
0)
02
#34000
b101 *
b101 -
b101 4
b101 8
b101 3
#35000
b100 E
b101 9
0%
b101 ,
b101 =
1)
12
#36000
1D
1(
1@
1#
0?
0"
0C
0'
#40000
0)
02
#45000
b100010 <
b100010 1
b100010 !
b100010 .
b100010 6
b100 9
b100 ,
b100 =
b10001 7
b10001 0
b10001 ;
1)
12
#50000
0)
02
#55000
b110011 <
b110011 1
b110011 !
b110011 .
b110011 6
b11 9
b11 ,
b11 =
b100010 7
b100010 0
b100010 ;
1)
12
#60000
0)
02
#65000
b1000100 <
b1000100 1
b1000100 !
b1000100 .
b1000100 6
b10 9
b10 ,
b10 =
b110011 7
b110011 0
b110011 ;
1)
12
#70000
0)
02
#75000
b1010101 <
b1010101 1
b1010101 !
b1010101 .
b1010101 6
b1 9
1%
b1 ,
b1 =
b1000100 7
b1000100 0
b1000100 ;
1)
12
#77000
b101 E
#78000
0@
0#
0D
0(
1A
1$
