Datapath_and_controller/boothmultiplier2/booth.v
`timescale 1ns/1ps
module booth (clk,rst,start,X,Y,Z,valid);
    input clk,rst,start;
    input signed [3:0] X,Y;
    output reg signed [7:0] Z;
    output reg valid;

    reg signed [7:0] next_Z, temp_Z;
    reg pre_state, next_state;
    reg next_valid; 
    reg [1:0] count, next_count;
    reg [1:0] temp, next_temp;
    parameter IDLE = 1'b0, START = 1'b1;

    always @(posedge clk or negedge rst) 
    begin
        if (!rst)
        begin
            Z <= 8'd0;
            pre_state <= 1'b0;
            valid <= 1'b0;
            count <= 2'd0;
            temp <= 2'd0;
        end
        else
        begin
            Z <= next_Z;
            pre_state <= next_state;
            valid <= next_valid;
            count <= next_count;
            temp <= next_temp;
        end
    end
    
    always @(*) begin
        case (pre_state)
            IDLE :
            begin
            next_count = 2'd0;
            next_valid = 1'b0;
            if(start)
            begin
                next_state = START;
                next_temp = {X[0],1'b0};
                next_Z = {4'd0,X[3:0]};
            end
            else
            begin
                next_state = pre_state;
                next_temp = 2'd0;
                next_Z = 8'd0;
            end
            end

            START :
            begin
            case (temp)
                2'b10 : temp_Z = {Z[7:4] - Y,Z[3:0]}; 
                2'b01 : temp_Z = {Z[7:4] + Y,Z[3:0]}; 
                default: temp_Z = Z;
            endcase 
            next_temp = {X[count + 1],X[count]};
            next_count = count + 1;
            next_Z = temp_Z >>> 1;
            next_valid = (&count) ? 1'b1 : 1'b0;
            next_state = (&count) ? IDLE : pre_state;
            end
        endcase
    end
endmodule

Datapath_and_controller/boothmultiplier2/boothtest.v
`timescale 1ns/1ps
module DUT;
    reg clk,rst,start;
    reg [3:0] X,Y;

    wire [7:0] Z;
    wire valid;

booth B1(clk,rst,start,X,Y,Z,valid);

    initial 
    begin
        clk = 1'b0;
        rst = 1'b0;
        start = 1'b0;
        X= 5;
        Y= 7;
        #200 $finish;
    end

    always #5 clk = ~clk;

    initial
    begin
        #10 start = 1'b1; rst = 1'b1;
        #10 start = 1'b0;
    end
    initial begin
        $monitor ("time=%0t valid =%b" ,$time , valid);
        $dumpvars (0,DUT); $dumpfile("booth.vcd");
    end

endmodule

Datapath_and_controller/boothmultiplier2/dump.vcd
$date
	Sat Mar 28 20:37:46 2026
$end
$version
	Icarus Verilog
$end
$timescale
	1ps
$end
$scope module DUT $end
$var wire 8 ! Z [7:0] $end
$var wire 1 " valid $end
$var reg 4 # X [3:0] $end
$var reg 4 $ Y [3:0] $end
$var reg 1 % clk $end
$var reg 1 & rst $end
$var reg 1 ' start $end
$scope module B1 $end
$var wire 4 ( X [3:0] $end
$var wire 4 ) Y [3:0] $end
$var wire 1 * clk $end
$var wire 1 + rst $end
$var wire 1 , start $end
$var reg 8 - Z [7:0] $end
$var reg 2 . count [1:0] $end
$var reg 8 / next_Z [7:0] $end
$var reg 2 0 next_count [1:0] $end
$var reg 1 1 next_state $end
$var reg 2 2 next_temp [1:0] $end
$var reg 1 3 next_valid $end
$var reg 1 4 pre_state $end
$var reg 2 5 temp [1:0] $end
$var reg 8 6 temp_Z [7:0] $end
$var reg 1 7 valid $end
$upscope $end
$upscope $end
$enddefinitions $end
#0
$dumpvars
07
bx 6
b0 5
04
03
b0 2
01
b0 0
b0 /
b0 .
b0 -
0,
0+
0*
b111 )
b101 (
0'
0&
0%
b111 $
b101 #
0"
b0 !
$end
#5000
1%
1*
#10000
b101 /
b10 2
11
0%
0*
1&
1+
1'
1,
#15000
b11001010 /
b1 0
b1 2
b10010101 6
b10 5
14
b101 -
b101 !
1%
1*
#20000
0%
0*
0'
0,
#25000
b11101 /
b10 0
b10 2
b111010 6
b1 5
b1 .
b11001010 -
b11001010 !
1%
1*
#30000
0%
0*
#35000
b11010110 /
b11 0
b1 2
b10101101 6
b10 5
b10 .
b11101 -
b11101 !
1%
1*
#40000
0%
0*
#45000
01
13
b100011 /
b0 0
bx0 2
b1000110 6
b1 5
b11 .
b11010110 -
b11010110 !
1%
1*
#50000
0%
0*
#55000
b0 /
b0 2
03
bx0 5
b0 .
17
1"
04
b100011 -
b100011 !
1%
1*
#60000
0%
0*
#65000
b0 5
07
0"
b0 -
b0 !
1%
1*
