basics/memorymodelling/32_32directregbank.v
`timescale 1ns/1ps
module regbank (clk,write,wrdata,sr1,sr2,dr,rddata1,rddata2);
    input clk,write;
    input [31:0] wrdata;
    input [4:0] sr1,sr2,dr;
    output [31:0] rddata1,rddata2;
    reg [31:0] regfile [31:0];

    assign rddata1 = regfile[sr1];
    assign rddata2 = regfile[sr2];

    always @(posedge clk) begin
        if (write) begin
            regfile [dr] = wrdata;
        end
    end
endmodule


// code for mux 32 X 1
/* 
    input [4:0] sel;
    input [31:0] X;
    output Y;
    
    assign Y = X[sel];
*/

basics/memorymodelling/4_32bitregtest.v
`timescale 1ns/1ps
module DUT;

    reg clk,write;
    reg [4:0] sr1,sr2,dr;
    reg [31:0] wrdata;

    wire [31:0] rddata1, rddata2;

    regbank R1(clk,write,wrdata,sr1,sr2,dr,rddata1,rddata2);

    always #5 clk = ~clk;

    initial begin
    clk = 0;
    write =0;
    sr1=0;
    sr2=0;
    dr=0;
    wrdata=0;

    #10
    write = 1;
    wrdata = 32'h100;
    
    #10
    dr =1;
    wrdata = 32'h200;

    #10
    dr =2;
    wrdata = 32'h300;

    #10
    dr =3;
    wrdata = 32'h400;

    #10
    write =0;
    sr1 = 0;
    sr2 = 1;

    #1
    $display("%d", rddata1);
    $display("%d", rddata2);

    #10
    sr1 = 2;
    sr2 = 3;

    #1
    $display("%d", rddata1);
    $display("%d", rddata2);

    #10
    $finish;
    end
    initial begin
        $dumpvars(0,DUT); $dumpfile("dump.vcd");
    end
endmodule

basics/memorymodelling/dump.vcd
$date
	Thu May 07 19:52:29 2026
$end
$version
	Icarus Verilog
$end
$timescale
	1ps
$end
$scope module DUT $end
$var wire 32 ! rddata1 [31:0] $end
$var wire 32 " rddata2 [31:0] $end
$var reg 1 # clk $end
$var reg 5 $ dr [4:0] $end
$var reg 5 % sr1 [4:0] $end
$var reg 5 & sr2 [4:0] $end
$var reg 32 ' wrdata [31:0] $end
$var reg 1 ( write $end
$scope module R1 $end
$var wire 1 ) clk $end
$var wire 5 * dr [4:0] $end
$var wire 32 + rddata1 [31:0] $end
$var wire 32 , rddata2 [31:0] $end
$var wire 5 - sr1 [4:0] $end
$var wire 5 . sr2 [4:0] $end
$var wire 32 / wrdata [31:0] $end
$var wire 1 0 write $end
$upscope $end
$upscope $end
$enddefinitions $end
#0
$dumpvars
00
b0 /
b0 .
b0 -
bx ,
bx +
b0 *
0)
0(
b0 '
b0 &
b0 %
b0 $
0#
bx "
bx !
$end
#5000
1#
1)
#10000
0#
0)
b100000000 '
b100000000 /
1(
10
#15000
b100000000 !
b100000000 +
b100000000 "
b100000000 ,
1#
1)
#20000
0#
0)
b1000000000 '
b1000000000 /
b1 $
b1 *
#25000
1#
1)
#30000
0#
0)
b1100000000 '
b1100000000 /
b10 $
b10 *
#35000
1#
1)
#40000
0#
0)
b10000000000 '
b10000000000 /
b11 $
b11 *
#45000
1#
1)
#50000
0#
0)
b1 &
b1 .
b1000000000 "
b1000000000 ,
0(
00
#55000
1#
1)
#60000
0#
0)
#61000
b11 &
b11 .
b10000000000 "
b10000000000 ,
b10 %
b10 -
b1100000000 !
b1100000000 +
