mips32proc/pipe_mips32.v
`timescale 1ns/1ps
module  pipe_mips32(clk1,clk2);

    input clk1,clk2; //take intr every two clk edge
    reg [31:0] IF_ID_IR,ID_EX_IR,EX_MEM_IR,MEM_WB_IR;
    reg TAKEN_BRANCH,HALTED,EX_MEM_COND;
    reg [5:0] PC,IF_ID_NPC,ID_EX_NPC;
    reg [31:0] mem[0:1023]; // 1024 instruction can be stored
    reg [31:0] EX_MEM_ALU,ID_EX_A,ID_EX_B,EX_MEM_B,MEM_WB_ALU,MEM_WB_LMD;
    reg [31:0] ID_EX_IMM;
    reg [2:0] ID_EX_TYPE,EX_MEM_TYPE,MEM_WB_TYPE;
    reg [31:0] REG[0:63];

    
    parameter ADD = 6'b000000,SUB = 6'b000001,AND = 6'b000010,OR = 6'b000011,SLT = 6'b000100,
              MUL = 6'b000101, HLT = 6'b111111, LW = 6'b001000, SW = 6'b001001,ADDI = 6'b001010,
              SUBI = 6'b001011,SLTI = 6'b001100, BNEQZ = 6'b001101, BEQZ = 6'b001110;
    
    parameter RR_ALU = 3'b000, RM_ALU = 3'b001, LOAD = 3'b010 ,STORE = 3'b011, BRANCH = 3'b100,
              HALT = 3'b101;

    always @(posedge clk1) begin // instr Fetch
        if (HALTED == 0) begin
            if (((EX_MEM_IR[31:26] == BEQZ) && (EX_MEM_COND == 1)) 
                || ((EX_MEM_IR[31:26] == BNEQZ) && (EX_MEM_COND == 0))) 
                begin
                    IF_ID_IR <= mem[EX_MEM_ALU];
                    TAKEN_BRANCH <= 1'b1;
                    IF_ID_NPC <= EX_MEM_ALU +1;
                    PC <= EX_MEM_ALU +1;
                end
            else
                begin
                    IF_ID_IR <= mem[PC];
                    IF_ID_NPC <= PC + 1;
                    PC <= PC + 1;
                end
        end
    end

    always @(posedge clk2) begin // instr decode
        if (HALTED == 0) 
        begin
            if (IF_ID_IR[25:21] == 5'b00000) // this suggest rs is 00000 means rs is R0
            begin
                ID_EX_A <= 0; // AND R0 is always 0 permanently
            end
            else
            begin
                ID_EX_A <= REG[IF_ID_IR[25:21]]; //rs ID_EX_A contains the vlue of inside rs
            end // rs contains the base memory address
            
            if (IF_ID_IR[20:16] == 5'b00000) 
            begin
                ID_EX_B <= 0;
            end
            else
            begin
                ID_EX_B <= REG[IF_ID_IR[20:16]]; //rt
            end

            ID_EX_NPC <= IF_ID_NPC;
            ID_EX_IR <= IF_ID_IR;
            ID_EX_IMM <= {{16{IF_ID_IR[15]}},{IF_ID_IR[15:0]}};


            case (IF_ID_IR[31:26])
                ADD,SUB,AND,OR,SLT,MUL: ID_EX_TYPE <= RR_ALU;
                ADDI,SUBI,SLTI  : ID_EX_TYPE <= RM_ALU;
                LW  : ID_EX_TYPE <= LOAD;
                SW  : ID_EX_TYPE <= STORE;
                BEQZ,BNEQZ  : ID_EX_TYPE <= BRANCH;
                HLT  : ID_EX_TYPE <= HALT;
                default: ID_EX_TYPE <= HALT;
            endcase
        end
    end

    always @(posedge clk1) begin //EXECUTION
        if (HALTED == 0) begin
            EX_MEM_IR <= ID_EX_IR;
            EX_MEM_TYPE <= ID_EX_TYPE;

            case (ID_EX_TYPE)
                RR_ALU : 
                begin
                    case (ID_EX_IR[31:26])
                        ADD : EX_MEM_ALU <= ID_EX_A + ID_EX_B;
                        SUB : EX_MEM_ALU <= ID_EX_A - ID_EX_B;
                        AND : EX_MEM_ALU <= ID_EX_A & ID_EX_B;
                        OR : EX_MEM_ALU <= ID_EX_A | ID_EX_B;
                        SLT : EX_MEM_ALU <= ID_EX_A < ID_EX_B;
                        MUL : EX_MEM_ALU <= ID_EX_A * ID_EX_B;
                        default: EX_MEM_ALU <= 32'hxxxxxxxx;
                    endcase
                end

                RM_ALU : 
                begin
                    case (ID_EX_IR[31:26])
                        ADDI : EX_MEM_ALU <= ID_EX_A + ID_EX_IMM;
                        SUBI : EX_MEM_ALU <= ID_EX_A - ID_EX_IMM;
                        SLTI : EX_MEM_ALU <= ID_EX_A < ID_EX_IMM;
                        default: EX_MEM_ALU <= 32'hxxxxxxxx;
                    endcase
                end

                LOAD, STORE :
                begin
                    EX_MEM_ALU <= ID_EX_A + ID_EX_IMM;
                    EX_MEM_B <= ID_EX_B;
                end

                BRANCH :
                begin
                    EX_MEM_ALU <= ID_EX_NPC + ID_EX_IMM;
                    EX_MEM_COND <= (ID_EX_A == 0);
                end

                HALT :
                begin
                    HALTED <= 1'b1;
                end

            endcase
        end
    end

    always @(posedge clk2) begin // memory stage 
        if (HALTED == 0) begin
            MEM_WB_TYPE <= EX_MEM_TYPE;
            MEM_WB_IR <= EX_MEM_IR;


            case (EX_MEM_TYPE)
                RR_ALU,RM_ALU :
                begin
                    MEM_WB_ALU <= EX_MEM_ALU;
                end

                LOAD :
                begin
                    MEM_WB_LMD <= mem[EX_MEM_ALU];
                end

                STORE :
                begin
                    mem[EX_MEM_ALU] <= EX_MEM_B ;
                end
            endcase
        end
    end

    always @(posedge clk1) begin //WB stage
            case (MEM_WB_TYPE)
                RR_ALU : REG[MEM_WB_IR[15:11]] <= MEM_WB_ALU; 
                RM_ALU : REG[MEM_WB_IR[20:16]] <= MEM_WB_ALU; 
                LOAD : REG[MEM_WB_IR[20:16]] <= MEM_WB_LMD;
                HALT : HALTED <= 1'b1;
            endcase
    end
endmodule

mips32proc/mips32test.v
`timescale 1ns/1ps
module DUT;

reg clk1,clk2;
integer k;

pipe_mips32 mips(clk1,clk2);

initial
begin
    clk1 = 0; clk2 =0;
    repeat(20)
    begin
        #5 clk1 = 1; #5 clk1 =0;
        #5 clk2 = 1; #5 clk2 =0;
    end
end

initial
begin
    for (k = 2; k<64; k = k + 1) begin
        mips.REG[k] = k;
    end
    mips.REG[0] = 0;
    mips.REG[1] = 0;
    /*mips.mem[0] = 32'h00430800; //ADD R1,R2,R3 0000 0000 0100 0011 0000 1000 0000 0000
    mips.mem[1] = 32'h04430800; //SUB R1,R2,R3 0000 0100 0100 0011 0000 1000 0000 0000
    mips.mem[2] = 32'h2841000A; //ADDI R1,R2,10 0010 1000 0100 0001 0000 0000 0000 1010
    mips.mem[3] = 32'h09631800; //OR R3,R3,R3 0000 1100 0110 0011 0001 1000 0000 0000
    mips.mem[4] = 32'h24410014; //SW R1,20(R2) 0010 0100 0100 0001 0000 0000 0001 0100
    mips.mem[5] = 32'hFC000000; //HLT
*/
    mips.mem[0] = 32'h00430800; //ADD R1,R2,R3 0000 0000 0100 0011 0000 1000 0000 0000
    mips.mem[1] = 32'h04630800; //SUB R1,R3,R3 0000 0100 0110 0011 0000 1000 0000 0000 // give time to update R1
    mips.mem[2] = 32'h09631800; //OR R3,R3,R3 0000 1100 0110 0011 0001 1000 0000 0000 [Empty instr.]
    mips.mem[3] = 32'h38200003; // BEQZ R1 0011 1000 0010 0000  0000 0000 0000 0011
    mips.mem[4] = 32'h09631800; //OR R3,R3,R3 0000 1100 0110 0011 0001 1000 0000 0000 [Empty instr.]
    mips.mem[5] = 32'h2841000A; //ADDI R1,R2,10 0010 1000 0100 0001 0000 0000 0000 1010
    mips.mem[6] = 32'h09631800; //OR R3,R3,R3 0000 1100 0110 0011 0001 1000 0000 0000
    mips.mem[7] = 32'h24410014; //SW R4,20(R2) 0010 0100 0100 0100 0000 0000 0001 0100
    mips.mem[8] = 32'hFC000000; //HLT 

    mips.PC = 0;
    mips.HALTED = 1'b0;
    mips.TAKEN_BRANCH = 1'b0;

    #400 $finish;
end

initial
begin
    $monitor("Time : %d, reg[1] : %d, val = %d, mem val : %d", $time, mips.REG[1], mips.EX_MEM_ALU, mips.mem[22]);
    $dumpfile("dump.vcd");
    $dumpvars(0,DUT);
end

endmodule

mips32proc/dump.vcd
$date
	Fri Jun 12 11:51:57 2026
$end
$version
	Icarus Verilog
$end
$timescale
	1ps
$end
$scope module DUT $end
$var reg 1 ! clk1 $end
$var reg 1 " clk2 $end
$var integer 32 # k [31:0] $end
$scope module mips $end
$var wire 1 $ clk1 $end
$var wire 1 % clk2 $end
$var reg 32 & EX_MEM_ALU [31:0] $end
$var reg 32 ' EX_MEM_B [31:0] $end
$var reg 1 ( EX_MEM_COND $end
$var reg 32 ) EX_MEM_IR [31:0] $end
$var reg 3 * EX_MEM_TYPE [2:0] $end
$var reg 1 + HALTED $end
$var reg 32 , ID_EX_A [31:0] $end
$var reg 32 - ID_EX_B [31:0] $end
$var reg 32 . ID_EX_IMM [31:0] $end
$var reg 32 / ID_EX_IR [31:0] $end
$var reg 6 0 ID_EX_NPC [5:0] $end
$var reg 3 1 ID_EX_TYPE [2:0] $end
$var reg 32 2 IF_ID_IR [31:0] $end
$var reg 6 3 IF_ID_NPC [5:0] $end
$var reg 32 4 MEM_WB_ALU [31:0] $end
$var reg 32 5 MEM_WB_IR [31:0] $end
$var reg 32 6 MEM_WB_LMD [31:0] $end
$var reg 3 7 MEM_WB_TYPE [2:0] $end
$var reg 6 8 PC [5:0] $end
$var reg 1 9 TAKEN_BRANCH $end
$upscope $end
$upscope $end
$enddefinitions $end
#0
$dumpvars
09
b0 8
bx 7
bx 6
bx 5
bx 4
bx 3
bx 2
bx 1
bx 0
bx /
bx .
bx -
bx ,
0+
bx *
bx )
x(
bx '
bx &
0%
0$
b1000000 #
0"
0!
$end
#5000
b1 8
b1 3
b10000110000100000000000 2
1!
1$
#10000
0!
0$
#15000
b0 1
b100000000000 .
b10000110000100000000000 /
b1 0
b11 -
b10 ,
1"
1%
#20000
0"
0%
#25000
b101 &
b0 *
b10000110000100000000000 )
b10 8
b10 3
b100011000110000100000000000 2
1!
1$
#30000
0!
0$
#35000
b101 4
b10000110000100000000000 5
b0 7
b100011000110000100000000000 /
b10 0
b11 ,
1"
1%
#40000
0"
0%
#45000
b11 8
b11 3
b1001011000110001100000000000 2
b0 &
b100011000110000100000000000 )
1!
1$
#50000
0!
0$
#55000
b1100000000000 .
b1001011000110001100000000000 /
b11 0
b1011 ,
b0 4
b100011000110000100000000000 5
1"
1%
#60000
0"
0%
#65000
b11 &
b1001011000110001100000000000 )
b100 8
b100 3
b111000001000000000000000000011 2
1!
1$
#70000
0!
0$
#75000
b11 4
b1001011000110001100000000000 5
b100 1
b11 .
b111000001000000000000000000011 /
b100 0
b0 -
b0 ,
1"
1%
#80000
0"
0%
#85000
b101 8
b101 3
b1001011000110001100000000000 2
1(
b111 &
b100 *
b111000001000000000000000000011 )
1!
1$
#90000
0!
0$
#95000
b0 1
b1100000000000 .
b1001011000110001100000000000 /
b101 0
b11 -
b1011 ,
b111000001000000000000000000011 5
b100 7
1"
1%
#100000
0"
0%
#105000
b11 &
b0 *
b1001011000110001100000000000 )
b1000 8
b1000 3
19
b100100010000010000000000010100 2
1!
1$
#110000
0!
0$
#115000
b1001011000110001100000000000 5
b0 7
b11 1
b10100 .
b100100010000010000000000010100 /
b1000 0
b0 -
b10 ,
1"
1%
#120000
0"
0%
#125000
b1001 8
b1001 3
b11111100000000000000000000000000 2
b0 '
b10110 &
b11 *
b100100010000010000000000010100 )
1!
1$
#130000
0!
0$
#135000
b101 1
b0 .
b11111100000000000000000000000000 /
b1001 0
b0 ,
b100100010000010000000000010100 5
b11 7
1"
1%
#140000
0"
0%
#145000
1+
b101 *
b11111100000000000000000000000000 )
b1010 8
b1010 3
bx 2
1!
1$
